ninox/__init__.py
ninox/ninox.py
ninox/api/__init__.py
ninox/api/adapter.py
ninox/models/__init__.py
ninox/models/workspace.py
ninox-0.1.0.dist-info/LICENSE
ninox-0.1.0.dist-info/METADATA
ninox-0.1.0.dist-info/WHEEL
ninox-0.1.0.dist-info/top_level.txt
ninox-0.1.0.dist-info/RECORD
